setup.py
lib/gitegginfo/__init__.py
lib/gitegginfo/commands.py
lib/gitegginfo/revision.py
lib/gitegginfo.egg-info/PKG-INFO
lib/gitegginfo.egg-info/SOURCES.txt
lib/gitegginfo.egg-info/dependency_links.txt
lib/gitegginfo.egg-info/entry_points.txt
lib/gitegginfo.egg-info/not-zip-safe
lib/gitegginfo.egg-info/requires.txt
lib/gitegginfo.egg-info/top_level.txt