Metadata-Version: 1.0
Name: gitegginfo
Version: 0.3
Summary: Setuptools extension to use Git version information
Home-page: http://github.com/trammell/gitegginfo
Author: John Trammell
Author-email: johntrammell@gmail.com
License: GPL
Keywords: setuptools egg_info git
Platform: UNKNOWN
Classifier: Programming Language :: Python
Classifier: Topic :: Software Development :: Libraries :: Python Modules
